setup.py
ppp_cas/__init__.py
ppp_cas/calchasLex.py
ppp_cas/calchasPreprocessing.py
ppp_cas/calchasTree.py
ppp_cas/calchasYacc.py
ppp_cas/config.py
ppp_cas/evaluator.py
ppp_cas/latexLex.py
ppp_cas/latexPreprocessing.py
ppp_cas/latexYacc.py
ppp_cas/mathematicaLex.py
ppp_cas/mathematicaTree.py
ppp_cas/mathematicaYacc.py
ppp_cas/notation.py
ppp_cas/parser.py
ppp_cas/requesthandler.py
ppp_cas/supyprocess.py
ppp_cas.egg-info/PKG-INFO
ppp_cas.egg-info/SOURCES.txt
ppp_cas.egg-info/dependency_links.txt
ppp_cas.egg-info/requires.txt
ppp_cas.egg-info/top_level.txt